vdom/__init__.py
vdom/_version.py
vdom/core.py
vdom/frozendict.py
vdom/helpers.py
vdom/logos.py
vdom/schemas/vdom_schema_v0.json
vdom/schemas/vdom_schema_v1.json
vdom/svg.py
vdom/tests/__init__.py
vdom/tests/test_core.py
vdom/tests/test_frozen.py
vdom-1.0.0.dist-info/LICENSE
vdom-1.0.0.dist-info/METADATA
vdom-1.0.0.dist-info/WHEEL
vdom-1.0.0.dist-info/RECORD
