Metadata-Version: 2.1
Name: vdom
Version: 1.0.0
Summary: 
Author: Kyle Kelley
Author-email: rgbkrk@gmail.com
Requires-Python: >=3.8,<4.0
Classifier: Programming Language :: Python :: 3
Classifier: Programming Language :: Python :: 3.8
Classifier: Programming Language :: Python :: 3.9
Classifier: Programming Language :: Python :: 3.10
Classifier: Programming Language :: Python :: 3.11
Requires-Dist: ipython (>=8.11.0,<9.0.0)
Requires-Dist: jsonschema (>=4.17.3,<5.0.0)
